decoder.v
module decoder #(
    parameter integer INSTR_SIZE = 14
) (
    input  wire [INSTR_SIZE-1:0] instruction,
    output reg                   jump_to
);

    always @(*) begin
        jump_to = 1'b0;                     // valor por defecto

        casez (instruction[13:11])
            3'b101:  jump_to = 1'b1;        // GOTO
            default: jump_to = 1'b0;
        endcase
    end

endmodule

mem.v
module mem (
    input  wire        clk,
    input  wire [4:0]  address,   // 5 bits -> 32 posiciones (0..31)
    output reg  [13:0] dato       // instruccion de 14 bits
);

    reg [13:0] rom [0:31];        // 32 palabras de 14 bits

    initial $readmemh("rom32x14.mem", rom);

    always @(posedge clk)
        dato <= rom[address];

endmodule

pc.v
module pc
#(
    parameter integer PC_SIZE = 13,
	parameter integer PC_K = 11
)
(
    input  wire               clk,
    input  wire               rst,
	input  wire				  jump,
	input  wire [PC_K-1:0] new_counter,
    output reg  [PC_SIZE-1:0] counter
);

    always @(posedge clk) begin
        if (rst) begin
            counter <= 0;                // reset: vuelve a la direccion 0
        end else begin
			if(jump) begin
				counter <= {{(PC_SIZE-PC_K){1'b0}}, new_counter};   // 00 + k (11 bits)
			end else begin
				counter <= counter + 1;      // avanza a la siguiente instruccion	
			end
        end
    end

endmodule

clk.v
module clk_div
#(
    parameter integer DIV = 24
)
(
    input  wire clk,
    output reg  clk_out
);

    reg [$clog2(DIV)-1:0] cnt;

    // Valores iniciales: sin esto la simulacion muestra 'x'
    initial begin
        cnt     = 0;
        clk_out = 1'b0;
    end

    always @(posedge clk) begin
        if (cnt == DIV/2 - 1) begin    // ya pasaron DIV/2 ciclos
            cnt     <= 0;              // reinicia el contador
            clk_out <= ~clk_out;       // invierte la salida
        end else begin
            cnt     <= cnt + 1;        // sigue contando
        end
    end

endmodule

sim/osch_sim.v
// osch_sim.v - Modelo del OSCH de Lattice (SOLO simulacion, no agregar a Diamond)
`timescale 1ns/1ps
module OSCH #(
    parameter NOM_FREQ = "12.09"
) (
    input  wire STDBY,
    output reg  OSC,
    output wire SEDSTDBY
);
    initial OSC = 1'b0;
    always #41.36 OSC = ~OSC;   // ~12.09 MHz
    assign SEDSTDBY = 1'b0;
endmodule

top.v
module top #(
    parameter integer DIV     = 12_090_000 / 3,   // 2 Hz: el PC avanza 2 veces por segundo
    parameter integer LEDS    = 8,
    parameter integer PC_SIZE = 13,
	parameter integer PC_K = 11
) (
    input  wire              rst_n,
    output wire [LEDS-1:0]   led
);

    wire               clk;
    wire               clk_out;
    wire [PC_SIZE-1:0] pc_counter; 
	wire [13:0] mem_data; 
	
	wire jump_to;

    OSCH #(.NOM_FREQ("12.09")) u_osc (
        .STDBY    (1'b0),
        .OSC      (clk),
        .SEDSTDBY ()
    );

    clk_div #(.DIV(DIV)) u_div (
        .clk     (clk),
        .clk_out (clk_out)
    );

	pc #(.PC_SIZE(PC_SIZE), .PC_K(PC_K)) u_pc (
		.clk         (clk_out),
		.rst         (~rst_n),
		.jump        (jump_to),
		.new_counter (mem_data[10:0]),
		.counter     (pc_counter)
	);

	mem u_mem (
		.clk     (clk_out),
		.address (pc_counter[4:0]),
		.dato    (mem_data)
	);
	
	decoder u_decoder 
	(
		.instruction (mem_data),
		.jump_to (jump_to)
	);

	assign led = ~mem_data[7:0];

endmodule

sim/tb_cpu_top.v
`timescale 1ns/1ps
// -----------------------------------------------------------------------------
// Testbench del CPU (top con PC + memoria + decoder).
//
// - Usa osch_sim.v como modelo del OSCH (solo simulacion).
// - Baja DIV a un valor chico para no esperar segundos de simulacion.
// - Imprime una linea por cada paso del PC (flanco de clk_out).
// - Auto-chequeo:
//     1) el PC nunca pasa de la direccion del GOTO + 1 (si pasa, el salto fallo
//        y esta recorriendo los NOP);
//     2) el programa da la vuelta al menos NUM_VUELTAS veces.
//
// Programa esperado en la memoria:
//   00..09: MOVLW (0x01,0x02,0x04,0x08,0x10,0x20,0x40,0x80,0xFF,0x00)
//   0A    : GOTO 0x000
// -----------------------------------------------------------------------------
module tb_cpu_top;

    localparam integer GOTO_ADDR   = 5'h0A;   // direccion del GOTO en la memoria
    localparam integer NUM_VUELTAS = 3;       // vueltas completas a observar
    localparam integer MAX_PASOS   = 200;     // tope de seguridad

    reg         rst_n;
    wire [7:0]  led;

    integer pasos;
    integer vueltas;
    integer errors;
    reg     visto_goto;

    // DIV chico: el PC avanza rapido en simulacion
    top #(
        .DIV     (4),
        .LEDS    (8),
        .PC_SIZE (13),
        .PC_K    (11)
    ) dut (
        .rst_n (rst_n),
        .led   (led)
    );

    // ---- Reset ---------------------------------------------------------------
    initial begin
        rst_n = 1'b0;
        #2000;
        rst_n = 1'b1;
    end

    // ---- Monitor y chequeos (un paso por flanco de clk_out) -------------------
    initial begin
        pasos      = 0;
        vueltas    = 0;
        errors     = 0;
        visto_goto = 0;
    end

    always @(posedge dut.clk_out) begin
        if (rst_n) begin
            pasos = pasos + 1;

            $display("t=%0t  paso=%3d  pc=%02h  instr=%04h  jump=%b  led=%b (~%02h)",
                     $time, pasos, dut.pc_counter[4:0], dut.mem_data,
                     dut.jump_to, led, ~led);

            // 1) El PC no debe pasar de GOTO_ADDR + 1
            //    (+1 porque con memoria sincrona el PC va un ciclo adelante)
            if (dut.pc_counter[4:0] > GOTO_ADDR + 1) begin
                $display("ERROR: pc=%02h paso de la direccion del GOTO (%02h). El salto no funciona.",
                         dut.pc_counter[4:0], GOTO_ADDR);
                errors = errors + 1;
            end

            // 2) Contar vueltas: el GOTO se ve en el bus de instruccion
            if (dut.jump_to) begin
                visto_goto = 1;
                vueltas    = vueltas + 1;
            end

            if (vueltas >= NUM_VUELTAS || pasos >= MAX_PASOS) begin
                if (!visto_goto) begin
                    $display("ERROR: jump_to nunca se activo.");
                    errors = errors + 1;
                end
                if (vueltas < NUM_VUELTAS) begin
                    $display("ERROR: solo %0d vueltas de %0d esperadas.", vueltas, NUM_VUELTAS);
                    errors = errors + 1;
                end

                if (errors == 0) $display("\nTB_CPU_TOP: PASS (%0d vueltas, %0d pasos)", vueltas, pasos);
                else             $display("\nTB_CPU_TOP: FAIL (%0d errores)", errors);
                $finish;
            end
        end
    end

    // ---- Formas de onda -------------------------------------------------------
    initial begin
        $dumpfile("test_cpu.vcd");
        $dumpvars(0, tb_cpu_top);
    end

endmodule

sim/test_cpu.vcd
$date
	Sat Oct  3 15:53:22 2026
$end
$version
	Icarus Verilog
$end
$timescale
	1ps
$end
$scope module tb_cpu_top $end
$var wire 8 ! led [7:0] $end
$var parameter 32 " GOTO_ADDR $end
$var parameter 32 # MAX_PASOS $end
$var parameter 32 $ NUM_VUELTAS $end
$var reg 1 % rst_n $end
$var reg 1 & visto_goto $end
$var integer 32 ' errors [31:0] $end
$var integer 32 ( pasos [31:0] $end
$var integer 32 ) vueltas [31:0] $end
$scope module dut $end
$var wire 8 * led [7:0] $end
$var wire 1 % rst_n $end
$var wire 13 + pc_counter [12:0] $end
$var wire 14 , mem_data [13:0] $end
$var wire 1 - jump_to $end
$var wire 1 . clk_out $end
$var wire 1 / clk $end
$var parameter 32 0 DIV $end
$var parameter 32 1 LEDS $end
$var parameter 32 2 PC_K $end
$var parameter 32 3 PC_SIZE $end
$scope module u_decoder $end
$var wire 14 4 instruction [13:0] $end
$var parameter 32 5 INSTR_SIZE $end
$var reg 1 - jump_to $end
$upscope $end
$scope module u_div $end
$var wire 1 / clk $end
$var parameter 32 6 DIV $end
$var reg 1 . clk_out $end
$var reg 2 7 cnt [1:0] $end
$upscope $end
$scope module u_mem $end
$var wire 5 8 address [4:0] $end
$var wire 1 . clk $end
$var reg 14 9 dato [13:0] $end
$upscope $end
$scope module u_osc $end
$var wire 1 : SEDSTDBY $end
$var wire 1 ; STDBY $end
$var parameter 40 < NOM_FREQ $end
$var reg 1 / OSC $end
$upscope $end
$scope module u_pc $end
$var wire 1 . clk $end
$var wire 1 - jump $end
$var wire 11 = new_counter [10:0] $end
$var wire 1 > rst $end
$var parameter 32 ? PC_K $end
$var parameter 32 @ PC_SIZE $end
$var reg 13 A counter [12:0] $end
$upscope $end
$upscope $end
$upscope $end
$enddefinitions $end
$comment Show the parameter values. $end
$dumpall
b1101 @
b1011 ?
b11000100110010001011100011000000111001 <
b100 6
b1110 5
b1101 3
b1011 2
b1000 1
b100 0
b11 $
b11001000 #
b1010 "
$end
#0
$dumpvars
bx A
1>
bx =
0;
0:
bx 9
bx 8
b0 7
bx 4
0/
0.
x-
bx ,
bx +
bx *
b0 )
b0 (
b0 '
0&
0%
bx !
$end
#41360
b1 7
1/
#82720
0/
#124080
b0 8
b0 +
b0 A
1.
b0 7
1/
#165440
0/
#206800
b1 7
1/
#248160
0/
#289520
0.
b0 7
1/
#330880
0/
#372240
b1 7
1/
#413600
0/
#454960
b11111110 !
b11111110 *
b1 =
0-
b11000000000001 ,
b11000000000001 4
b11000000000001 9
1.
b0 7
1/
#496320
0/
#537680
b1 7
1/
#579040
0/
#620400
0.
b0 7
1/
#661760
0/
#703120
b1 7
1/
#744480
0/
#785840
1.
b0 7
1/
#827200
0/
#868560
b1 7
1/
#909920
0/
#951280
0.
b0 7
1/
#992640
0/
#1034000
b1 7
1/
#1075360
0/
#1116720
1.
b0 7
1/
#1158080
0/
#1199440
b1 7
1/
#1240800
0/
#1282160
0.
b0 7
1/
#1323520
0/
#1364880
b1 7
1/
#1406240
0/
#1447600
1.
b0 7
1/
#1488960
0/
#1530320
b1 7
1/
#1571680
0/
#1613040
0.
b0 7
1/
#1654400
0/
#1695760
b1 7
1/
#1737120
0/
#1778480
1.
b0 7
1/
#1819840
0/
#1861200
b1 7
1/
#1902560
0/
#1943920
0.
b0 7
1/
#1985280
0/
#2000000
0>
1%
#2026640
b1 7
1/
#2068000
0/
#2109360
b1 8
b1 +
b1 A
b1 (
1.
b0 7
1/
#2150720
0/
#2192080
b1 7
1/
#2233440
0/
#2274800
0.
b0 7
1/
#2316160
0/
#2357520
b1 7
1/
#2398880
0/
#2440240
b11111101 !
b11111101 *
b10 =
b10 8
b11000000000010 ,
b11000000000010 4
b11000000000010 9
b10 +
b10 A
b10 (
1.
b0 7
1/
#2481600
0/
#2522960
b1 7
1/
#2564320
0/
#2605680
0.
b0 7
1/
#2647040
0/
#2688400
b1 7
1/
#2729760
0/
#2771120
b11111011 !
b11111011 *
b11 8
b100 =
b11 +
b11 A
b11000000000100 ,
b11000000000100 4
b11000000000100 9
b11 (
1.
b0 7
1/
#2812480
0/
#2853840
b1 7
1/
#2895200
0/
#2936560
0.
b0 7
1/
#2977920
0/
#3019280
b1 7
1/
#3060640
0/
#3102000
b11110111 !
b11110111 *
b1000 =
b100 8
b11000000001000 ,
b11000000001000 4
b11000000001000 9
b100 +
b100 A
b100 (
1.
b0 7
1/
#3143360
0/
#3184720
b1 7
1/
#3226080
0/
#3267440
0.
b0 7
1/
#3308800
0/
#3350160
b1 7
1/
#3391520
0/
#3432880
b11101111 !
b11101111 *
b101 8
b10000 =
b101 +
b101 A
b11000000010000 ,
b11000000010000 4
b11000000010000 9
b101 (
1.
b0 7
1/
#3474240
0/
#3515600
b1 7
1/
#3556960
0/
#3598320
0.
b0 7
1/
#3639680
0/
#3681040
b1 7
1/
#3722400
0/
#3763760
b11011111 !
b11011111 *
b100000 =
b110 8
b11000000100000 ,
b11000000100000 4
b11000000100000 9
b110 +
b110 A
b110 (
1.
b0 7
1/
#3805120
0/
#3846480
b1 7
1/
#3887840
0/
#3929200
0.
b0 7
1/
#3970560
0/
#4011920
b1 7
1/
#4053280
0/
#4094640
b10111111 !
b10111111 *
b111 8
b1000000 =
b111 +
b111 A
b11000001000000 ,
b11000001000000 4
b11000001000000 9
b111 (
1.
b0 7
1/
#4136000
0/
#4177360
b1 7
1/
#4218720
0/
#4260080
0.
b0 7
1/
#4301440
0/
#4342800
b1 7
1/
#4384160
0/
#4425520
b1111111 !
b1111111 *
b10000000 =
b1000 8
b11000010000000 ,
b11000010000000 4
b11000010000000 9
b1000 +
b1000 A
b1000 (
1.
b0 7
1/
#4466880
0/
#4508240
b1 7
1/
#4549600
0/
#4590960
0.
b0 7
1/
#4632320
0/
#4673680
b1 7
1/
#4715040
0/
#4756400
b0 !
b0 *
b1001 8
b11111111 =
b1001 +
b1001 A
b11000011111111 ,
b11000011111111 4
b11000011111111 9
b1001 (
1.
b0 7
1/
#4797760
0/
#4839120
b1 7
1/
#4880480
0/
#4921840
0.
b0 7
1/
#4963200
0/
#5004560
b1 7
1/
#5045920
0/
#5087280
b11111111 !
b11111111 *
b0 =
b1010 8
b11000000000000 ,
b11000000000000 4
b11000000000000 9
b1010 +
b1010 A
b1010 (
1.
b0 7
1/
#5128640
0/
#5170000
b1 7
1/
#5211360
0/
#5252720
0.
b0 7
1/
#5294080
0/
#5335440
b1 7
1/
#5376800
0/
#5418160
b1011 8
1-
b1011 +
b1011 A
b10100000000000 ,
b10100000000000 4
b10100000000000 9
b1011 (
1.
b0 7
1/
#5459520
0/
#5500880
b1 7
1/
#5542240
0/
#5583600
0.
b0 7
1/
#5624960
0/
#5666320
b1 7
1/
#5707680
0/
#5749040
0-
b0 8
b0 ,
b0 4
b0 9
b0 +
b0 A
b1 )
1&
b1100 (
1.
b0 7
1/
#5790400
0/
#5831760
b1 7
1/
#5873120
0/
#5914480
0.
b0 7
1/
#5955840
0/
#5997200
b1 7
1/
#6038560
0/
#6079920
b11111110 !
b11111110 *
b1 8
b1 =
b1 +
b1 A
b11000000000001 ,
b11000000000001 4
b11000000000001 9
b1101 (
1.
b0 7
1/
#6121280
0/
#6162640
b1 7
1/
#6204000
0/
#6245360
0.
b0 7
1/
#6286720
0/
#6328080
b1 7
1/
#6369440
0/
#6410800
b11111101 !
b11111101 *
b10 =
b10 8
b11000000000010 ,
b11000000000010 4
b11000000000010 9
b10 +
b10 A
b1110 (
1.
b0 7
1/
#6452160
0/
#6493520
b1 7
1/
#6534880
0/
#6576240
0.
b0 7
1/
#6617600
0/
#6658960
b1 7
1/
#6700320
0/
#6741680
b11111011 !
b11111011 *
b11 8
b100 =
b11 +
b11 A
b11000000000100 ,
b11000000000100 4
b11000000000100 9
b1111 (
1.
b0 7
1/
#6783040
0/
#6824400
b1 7
1/
#6865760
0/
#6907120
0.
b0 7
1/
#6948480
0/
#6989840
b1 7
1/
#7031200
0/
#7072560
b11110111 !
b11110111 *
b1000 =
b100 8
b11000000001000 ,
b11000000001000 4
b11000000001000 9
b100 +
b100 A
b10000 (
1.
b0 7
1/
#7113920
0/
#7155280
b1 7
1/
#7196640
0/
#7238000
0.
b0 7
1/
#7279360
0/
#7320720
b1 7
1/
#7362080
0/
#7403440
b11101111 !
b11101111 *
b101 8
b10000 =
b101 +
b101 A
b11000000010000 ,
b11000000010000 4
b11000000010000 9
b10001 (
1.
b0 7
1/
#7444800
0/
#7486160
b1 7
1/
#7527520
0/
#7568880
0.
b0 7
1/
#7610240
0/
#7651600
b1 7
1/
#7692960
0/
#7734320
b11011111 !
b11011111 *
b100000 =
b110 8
b11000000100000 ,
b11000000100000 4
b11000000100000 9
b110 +
b110 A
b10010 (
1.
b0 7
1/
#7775680
0/
#7817040
b1 7
1/
#7858400
0/
#7899760
0.
b0 7
1/
#7941120
0/
#7982480
b1 7
1/
#8023840
0/
#8065200
b10111111 !
b10111111 *
b111 8
b1000000 =
b111 +
b111 A
b11000001000000 ,
b11000001000000 4
b11000001000000 9
b10011 (
1.
b0 7
1/
#8106560
0/
#8147920
b1 7
1/
#8189280
0/
#8230640
0.
b0 7
1/
#8272000
0/
#8313360
b1 7
1/
#8354720
0/
#8396080
b1111111 !
b1111111 *
b10000000 =
b1000 8
b11000010000000 ,
b11000010000000 4
b11000010000000 9
b1000 +
b1000 A
b10100 (
1.
b0 7
1/
#8437440
0/
#8478800
b1 7
1/
#8520160
0/
#8561520
0.
b0 7
1/
#8602880
0/
#8644240
b1 7
1/
#8685600
0/
#8726960
b0 !
b0 *
b1001 8
b11111111 =
b1001 +
b1001 A
b11000011111111 ,
b11000011111111 4
b11000011111111 9
b10101 (
1.
b0 7
1/
#8768320
0/
#8809680
b1 7
1/
#8851040
0/
#8892400
0.
b0 7
1/
#8933760
0/
#8975120
b1 7
1/
#9016480
0/
#9057840
b11111111 !
b11111111 *
b0 =
b1010 8
b11000000000000 ,
b11000000000000 4
b11000000000000 9
b1010 +
b1010 A
b10110 (
1.
b0 7
1/
#9099200
0/
#9140560
b1 7
1/
#9181920
0/
#9223280
0.
b0 7
1/
#9264640
0/
#9306000
b1 7
1/
#9347360
0/
#9388720
b1011 8
1-
b1011 +
b1011 A
b10100000000000 ,
b10100000000000 4
b10100000000000 9
b10111 (
1.
b0 7
1/
#9430080
0/
#9471440
b1 7
1/
#9512800
0/
#9554160
0.
b0 7
1/
#9595520
0/
#9636880
b1 7
1/
#9678240
0/
#9719600
0-
b0 8
b0 ,
b0 4
b0 9
b0 +
b0 A
b10 )
b11000 (
1.
b0 7
1/
#9760960
0/
#9802320
b1 7
1/
#9843680
0/
#9885040
0.
b0 7
1/
#9926400
0/
#9967760
b1 7
1/
#10009120
0/
#10050480
b11111110 !
b11111110 *
b1 8
b1 =
b1 +
b1 A
b11000000000001 ,
b11000000000001 4
b11000000000001 9
b11001 (
1.
b0 7
1/
#10091840
0/
#10133200
b1 7
1/
#10174560
0/
#10215920
0.
b0 7
1/
#10257280
0/
#10298640
b1 7
1/
#10340000
0/
#10381360
b11111101 !
b11111101 *
b10 =
b10 8
b11000000000010 ,
b11000000000010 4
b11000000000010 9
b10 +
b10 A
b11010 (
1.
b0 7
1/
#10422720
0/
#10464080
b1 7
1/
#10505440
0/
#10546800
0.
b0 7
1/
#10588160
0/
#10629520
b1 7
1/
#10670880
0/
#10712240
b11111011 !
b11111011 *
b11 8
b100 =
b11 +
b11 A
b11000000000100 ,
b11000000000100 4
b11000000000100 9
b11011 (
1.
b0 7
1/
#10753600
0/
#10794960
b1 7
1/
#10836320
0/
#10877680
0.
b0 7
1/
#10919040
0/
#10960400
b1 7
1/
#11001760
0/
#11043120
b11110111 !
b11110111 *
b1000 =
b100 8
b11000000001000 ,
b11000000001000 4
b11000000001000 9
b100 +
b100 A
b11100 (
1.
b0 7
1/
#11084480
0/
#11125840
b1 7
1/
#11167200
0/
#11208560
0.
b0 7
1/
#11249920
0/
#11291280
b1 7
1/
#11332640
0/
#11374000
b11101111 !
b11101111 *
b101 8
b10000 =
b101 +
b101 A
b11000000010000 ,
b11000000010000 4
b11000000010000 9
b11101 (
1.
b0 7
1/
#11415360
0/
#11456720
b1 7
1/
#11498080
0/
#11539440
0.
b0 7
1/
#11580800
0/
#11622160
b1 7
1/
#11663520
0/
#11704880
b11011111 !
b11011111 *
b100000 =
b110 8
b11000000100000 ,
b11000000100000 4
b11000000100000 9
b110 +
b110 A
b11110 (
1.
b0 7
1/
#11746240
0/
#11787600
b1 7
1/
#11828960
0/
#11870320
0.
b0 7
1/
#11911680
0/
#11953040
b1 7
1/
#11994400
0/
#12035760
b10111111 !
b10111111 *
b111 8
b1000000 =
b111 +
b111 A
b11000001000000 ,
b11000001000000 4
b11000001000000 9
b11111 (
1.
b0 7
1/
#12077120
0/
#12118480
b1 7
1/
#12159840
0/
#12201200
0.
b0 7
1/
#12242560
0/
#12283920
b1 7
1/
#12325280
0/
#12366640
b1111111 !
b1111111 *
b10000000 =
b1000 8
b11000010000000 ,
b11000010000000 4
b11000010000000 9
b1000 +
b1000 A
b100000 (
1.
b0 7
1/
#12408000
0/
#12449360
b1 7
1/
#12490720
0/
#12532080
0.
b0 7
1/
#12573440
0/
#12614800
b1 7
1/
#12656160
0/
#12697520
b0 !
b0 *
b1001 8
b11111111 =
b1001 +
b1001 A
b11000011111111 ,
b11000011111111 4
b11000011111111 9
b100001 (
1.
b0 7
1/
#12738880
0/
#12780240
b1 7
1/
#12821600
0/
#12862960
0.
b0 7
1/
#12904320
0/
#12945680
b1 7
1/
#12987040
0/
#13028400
b11111111 !
b11111111 *
b0 =
b1010 8
b11000000000000 ,
b11000000000000 4
b11000000000000 9
b1010 +
b1010 A
b100010 (
1.
b0 7
1/
#13069760
0/
#13111120
b1 7
1/
#13152480
0/
#13193840
0.
b0 7
1/
#13235200
0/
#13276560
b1 7
1/
#13317920
0/
#13359280
b1011 8
1-
b1011 +
b1011 A
b10100000000000 ,
b10100000000000 4
b10100000000000 9
b100011 (
1.
b0 7
1/
#13400640
0/
#13442000
b1 7
1/
#13483360
0/
#13524720
0.
b0 7
1/
#13566080
0/
#13607440
b1 7
1/
#13648800
0/
#13690160
0-
b0 8
b0 ,
b0 4
b0 9
b0 +
b0 A
b11 )
b100100 (
1.
b0 7
1/
